LICENCE.txt
README.md
setup.py
draper_utils/__init__.py
draper_utils/admin.py
draper_utils/apps.py
draper_utils/models.py
draper_utils/tests.py
draper_utils/utils.py
draper_utils/views.py
draper_utils.egg-info/PKG-INFO
draper_utils.egg-info/SOURCES.txt
draper_utils.egg-info/dependency_links.txt
draper_utils.egg-info/not-zip-safe
draper_utils.egg-info/requires.txt
draper_utils.egg-info/top_level.txt
draper_utils/management/__init__.py
draper_utils/management/commands/__init__.py
draper_utils/management/commands/import_legacy_users.py
draper_utils/management/commands/import_projects.py
draper_utils/management/commands/setup_project_center.py
draper_utils/migrations/__init__.py
draper_utils/sql/list_project_activities.sql
draper_utils/sql/list_project_assigned_users.sql
draper_utils/sql/list_project_categories.sql
draper_utils/sql/list_project_stages.sql
draper_utils/sql/list_project_statuses.sql
draper_utils/sql/list_project_users.sql
draper_utils/sql/list_projects.sql
draper_utils/sql/list_users.sql