Metadata-Version: 2.1
Name: draper-utils
Version: 1.2
Summary: Project Management Module for Django - Utils
Home-page: https://github.com/pdbethke/draper-utils
Author: siteshell.net
Author-email: pdbethke@siteshell.net
License: LICENSE.txt
Platform: OS Independent
License-File: LICENCE.txt
